django_openacct-0.0.5.dist-info/DESCRIPTION.rst
django_openacct-0.0.5.dist-info/LICENSE.txt
django_openacct-0.0.5.dist-info/METADATA
django_openacct-0.0.5.dist-info/RECORD
django_openacct-0.0.5.dist-info/WHEEL
django_openacct-0.0.5.dist-info/metadata.json
django_openacct-0.0.5.dist-info/top_level.txt
openacct/__init__.py
openacct/admin.py
openacct/apps.py
openacct/forms.py
openacct/models.py
openacct/shortcuts.py
openacct/tests.py
openacct/urls.py
openacct/views.py
openacct/migrations/0001_initial.py
openacct/migrations/0002_default_project.py
openacct/migrations/__init__.py
