Metadata-Version: 2.0
Name: django-openacct
Version: 0.0.5
Summary: A pluggable Django app for managing research computing center project accounting.
Home-page: https://github.com/Elemnir/django-openacct
Author: Adam Howard
Author-email: ahoward@utk.edu
Maintainer: Adam Howard
Maintainer-email: ahoward@utk.edu
License: BSD 3-clause
Platform: UNKNOWN
Classifier: Environment :: Web Environment
Classifier: Framework :: Django
Classifier: Framework :: Django :: 2.2
Classifier: Intended Audience :: Developers
Classifier: License :: OSI Approved :: BSD License
Classifier: Operating System :: OS Independent
Classifier: Programming Language :: Python
Classifier: Programming Language :: Python :: 3
Classifier: Programming Language :: Python :: 3.6
Classifier: Programming Language :: Python :: 3.7
Classifier: Programming Language :: Python :: 3.8
Classifier: Topic :: Internet :: WWW/HTTP
Classifier: Topic :: Internet :: WWW/HTTP :: Dynamic Content
